rolling/__init__.py
rolling/apply.py
rolling/apply_pairwise.py
rolling/base.py
rolling/base_pairwise.py
rolling/entropy.py
rolling/hash.py
rolling/matching.py
rolling/minmax.py
rolling/monotonic.py
rolling/similarity.py
rolling/arithmetic/__init__.py
rolling/arithmetic/nunique.py
rolling/arithmetic/product.py
rolling/arithmetic/sum.py
rolling/logical/__init__.py
rolling/logical/all.py
rolling/logical/any.py
rolling/stats/__init__.py
rolling/stats/kurtosis.py
rolling/stats/mean.py
rolling/stats/median.py
rolling/stats/mode.py
rolling/stats/skew.py
rolling/stats/variance.py
rolling/structures/__init__.py
rolling/structures/bicounter.py
rolling/structures/skiplist.py
rolling/structures/sortedlist.py
rolling-0.5.0.dist-info/LICENSE
rolling-0.5.0.dist-info/METADATA
rolling-0.5.0.dist-info/WHEEL
rolling-0.5.0.dist-info/top_level.txt
rolling-0.5.0.dist-info/RECORD
