Metadata-Version: 2.1
Name: rolling
Version: 0.5.0
Summary: Efficient rolling window algorithms
Author: Alex Riley
License: MIT
Project-URL: Source, https://github.com/ajcr/rolling/
Project-URL: Tracker, https://github.com/ajcr/rolling/issues
Keywords: rolling window iterator algorithms
Classifier: Development Status :: 3 - Alpha
Classifier: Intended Audience :: Developers
Classifier: Topic :: Software Development :: Libraries :: Python Modules
Classifier: License :: OSI Approved :: MIT License
Classifier: Programming Language :: Python :: 3
Classifier: Programming Language :: Python :: 3.7
Classifier: Programming Language :: Python :: 3.8
Classifier: Programming Language :: Python :: 3.9
Classifier: Programming Language :: Python :: 3.10
Classifier: Programming Language :: Python :: 3.11
Requires-Python: >=3.7.0
License-File: LICENSE
